{
  "type": "minecraft:crafting_shaped",
  "category": "redstone",
  "group": "polyfactory:windmill_sail",
  "key": {
    "c": {
      "item": "minecraft:black_wool"
    },
    "s": {
      "item": "minecraft:stick"
    },
    "w": {
      "item": "polyfactory:wooden_plate"
    }
  },
  "pattern": [
    " sw",
    " ws",
    "wsc"
  ],
  "result": {
    "factorytools:nbt": {
      "display": {
        "color": 1908001
      }
    },
    "item": "polyfactory:windmill_sail"
  },
  "show_notification": true
}